Metadata-Version: 2.1
Name: pyOfferUp
Version: 0.3
Summary: Scrape data from offerup.com
Home-page: https://github.com/oscar0812/pyOfferUp
Download-URL: https://github.com/oscar0812/pyOfferUp/archive/refs/tags/v_03.tar.gz
Author: Oscar R. Torres
Author-email: oscar0812torres@gmail.com
License: apache-2.0
Keywords: OFFERUP,BUYING,SCRAPER,BITTLE
Classifier: Development Status :: 3 - Alpha
Classifier: Intended Audience :: Developers
Classifier: Topic :: Software Development :: Build Tools
Classifier: License :: OSI Approved :: Apache Software License
Classifier: Programming Language :: Python :: 3
Classifier: Programming Language :: Python :: 3.4
Classifier: Programming Language :: Python :: 3.5
Classifier: Programming Language :: Python :: 3.6
Classifier: Programming Language :: Python :: 3.7
Classifier: Programming Language :: Python :: 3.8
License-File: LICENSE.txt
